README.md
setup.cfg
setup.py
cardsdk/__init__.py
cardsdk/build.py
cardsdk/core.py
cardsdk/environment.py
cardsdk/gui.py
cardsdk/util.py
cardsdk/watch.py
cardsdk.egg-info/PKG-INFO
cardsdk.egg-info/SOURCES.txt
cardsdk.egg-info/dependency_links.txt
cardsdk.egg-info/entry_points.txt
cardsdk.egg-info/requires.txt
cardsdk.egg-info/top_level.txt
cardsdk.egg-info/zip-safe