Metadata-Version: 2.1
Name: cardsdk
Version: 0.5.7
Summary: CardSDK Scaffold CLI
Home-page: https://github.com/sopig
Author: chay0103
Author-email: chay0103@163.com
License: MIT
Platform: UNKNOWN
